uasu/__init__.py
uasu/cli.py
uasu-0.0.1.dist-info/LICENSE
uasu-0.0.1.dist-info/METADATA
uasu-0.0.1.dist-info/WHEEL
uasu-0.0.1.dist-info/entry_points.txt
uasu-0.0.1.dist-info/top_level.txt
uasu-0.0.1.dist-info/RECORD
