Metadata-Version: 2.1
Name: uasu
Version: 0.0.1
Requires-Python: >=3.10.2
License-File: LICENSE
Requires-Dist: google-cloud-storage
